wechatrobot/__init__.py
wechatrobot/wechat_robot.py
wechatrobot-1.0.6.dist-info/METADATA
wechatrobot-1.0.6.dist-info/WHEEL
wechatrobot-1.0.6.dist-info/top_level.txt
wechatrobot-1.0.6.dist-info/RECORD
