Metadata-Version: 2.1
Name: wechatrobot
Version: 1.0.6
Summary: send message to wechat robot
Home-page: https://github.com/x-hezhang/wechat-robot
Author: zhanghe
Author-email: x_hezhang@126.com
License: GNU GPLv3
Keywords: wechat,robot,wechatrobot,wechat-robot,wechat-webhook
Platform: UNKNOWN
Requires-Dist: requests
